[
  {
    "foto": "01_editada.png",
    "nombre": "A",
    "numero": "01",
    "texto": ""
  },
  {
    "numero": "02",
    "nombre": "B",
    "texto": "",
    "foto": "02_editada.png"
  },
  {
    "numero": "03",
    "nombre": "C",
    "texto": "",
    "foto": "03_editada.png"
  },
  {
    "numero": "04",
    "nombre": "D",
    "texto": "",
    "foto": "04_editada.png"
  },
  {
    "numero": "05",
    "nombre": "E",
    "texto": "",
    "foto": "05_editada.png"
  },
  {
    "numero": "06",
    "nombre": "F",
    "texto": "",
    "foto": "06_editada.png"
  }
]